mycalculator/__init__.py
mycalculator/api_helper.py
mycalculator/configuration.py
mycalculator/decorators.py
mycalculator/mycalculator_client.py
mycalculator/controllers/__init__.py
mycalculator/controllers/base_controller.py
mycalculator/controllers/simple_calculator_controller.py
mycalculator/exceptions/__init__.py
mycalculator/exceptions/api_exception.py
mycalculator/http/__init__.py
mycalculator/http/http_call_back.py
mycalculator/http/http_client.py
mycalculator/http/http_method_enum.py
mycalculator/http/http_request.py
mycalculator/http/http_response.py
mycalculator/http/requests_client.py
mycalculator/models/__init__.py
mycalculator/models/operation_enum.py
mycalculator/models/operation_type_enum.py
mycalculator/utilities/__init__.py
mycalculator/utilities/file_wrapper.py
tests/__init__.py
tests/http_response_catcher.py
tests/test_helper.py
tests/controllers/__init__.py
tests/controllers/controller_test_base.py
tests/controllers/test_simple_calculator_controller.py
apimatic_calculator_py-1.0.dist-info/LICENSE
apimatic_calculator_py-1.0.dist-info/METADATA
apimatic_calculator_py-1.0.dist-info/WHEEL
apimatic_calculator_py-1.0.dist-info/top_level.txt
apimatic_calculator_py-1.0.dist-info/RECORD
