Metadata-Version: 2.1
Name: apimatic-calculator-py
Version: 1.0
Summary: Calculator API built with APIMATIC
Home-page: https://apimatic.io
Author: Nida
Author-email: nida.zamir@apimatic.io
License: UNKNOWN
Platform: UNKNOWN
Requires-Dist: requests (<3.0,>=2.9.1)
Requires-Dist: jsonpickle (<1.0,>=0.7.1)
Requires-Dist: cachecontrol (<1.0,>=0.11.7)
Requires-Dist: python-dateutil (<3.0,>=2.5.3)
Requires-Dist: enum34 (>=1.1.6)
